VDR/VDR.py
VDR/VDR_Call.py
VDR/VDR_Indep.py
VDR/VDR_Indep_auto.py
VDR/VDR_methods.py
VDR/VDR_param.py
VDR/__init__.py
VDR/calc_params.py
VDR/combine_replicas.py
gamdvdr/VDR.py
gamdvdr/VDR_Indep.py
gamdvdr/VDR_methods.py
gamdvdr/VDR_param.py
gamdvdr/__init__.py
gamdvdr/combine_replicas.py
gamdvdr-1.0.0.dist-info/LICENSE
gamdvdr-1.0.0.dist-info/METADATA
gamdvdr-1.0.0.dist-info/WHEEL
gamdvdr-1.0.0.dist-info/entry_points.txt
gamdvdr-1.0.0.dist-info/top_level.txt
gamdvdr-1.0.0.dist-info/RECORD
