Metadata-Version: 2.1
Name: gamdvdr
Version: 1.0.0
Summary: Variable Density Reweighting for GaMD Simulations
Home-page: https://pypi.org/project/gamdvdr/
Author: Steven Turner
Author-email: S.C.Turner@soton.ac.uk
License: MIT
Classifier: License :: OSI Approved :: MIT License
Classifier: Programming Language :: Python
Classifier: Programming Language :: Python :: 3
Classifier: Programming Language :: Python :: 3.6
Classifier: Programming Language :: Python :: Implementation :: CPython
Classifier: Programming Language :: Python :: Implementation :: PyPy
Requires-Python: >=3.6
License-File: LICENSE
Requires-Dist: numpy
Requires-Dist: MDAnalysis
Requires-Dist: scipy (>=1.10.1)
Requires-Dist: argparse
Requires-Dist: matplotlib
Requires-Dist: pandas
Requires-Dist: scikit-learn
Requires-Dist: multiprocess
